odoo/addons/ssi_lead_data_requirement/README.rst
odoo/addons/ssi_lead_data_requirement/__init__.py
odoo/addons/ssi_lead_data_requirement/__manifest__.py
odoo/addons/ssi_lead_data_requirement/i18n/ssi_lead_data_requirement.pot
odoo/addons/ssi_lead_data_requirement/models/__init__.py
odoo/addons/ssi_lead_data_requirement/models/crm_lead.py
odoo/addons/ssi_lead_data_requirement/static/description/icon.png
odoo14_addon_ssi_lead_data_requirement-14.0.1.1.0.dist-info/METADATA
odoo14_addon_ssi_lead_data_requirement-14.0.1.1.0.dist-info/WHEEL
odoo14_addon_ssi_lead_data_requirement-14.0.1.1.0.dist-info/top_level.txt
odoo14_addon_ssi_lead_data_requirement-14.0.1.1.0.dist-info/RECORD
